streamauc/__init__.py
streamauc/plot_util.py
streamauc/streaming_metrics.py
streamauc/utils.py
streamauc/metrics/__init__.py
streamauc/metrics/_accuracy.py
streamauc/metrics/_f1_score.py
streamauc/metrics/_fnr.py
streamauc/metrics/_fpr.py
streamauc/metrics/_jaccard_index.py
streamauc/metrics/_precision.py
streamauc/metrics/_tnr.py
streamauc/metrics/_tpr.py
streamauc/metrics/metric_synonyms.py
tests/metrics/__init__.py
tests/metrics/test_accuracy.py
tests/metrics/test_f1_score.py
tests/metrics/test_fnr.py
tests/metrics/test_fpr.py
tests/metrics/test_jaccard.py
tests/metrics/test_precision.py
tests/metrics/test_tnr.py
tests/metrics/test_tpr.py
tests/utils/__init__.py
tests/utils/test_plots.py
tests/utils/test_util.py
streamauc-0.1.5.dist-info/LICENSE
streamauc-0.1.5.dist-info/METADATA
streamauc-0.1.5.dist-info/WHEEL
streamauc-0.1.5.dist-info/top_level.txt
streamauc-0.1.5.dist-info/RECORD
