Metadata-Version: 2.1
Name: streamauc
Version: 0.1.5
Summary: Stream and minibatch based metrics for probabilistic multi-class classification.
Home-page: https://github.com/FabricioArendTorres/streamAUC/
Author: Fabricio Arend Torres
License-File: LICENSE
Requires-Dist: numpy
Requires-Dist: matplotlib
Requires-Dist: numba
Provides-Extra: test
Requires-Dist: pytest ; extra == 'test'
Requires-Dist: coverage ; extra == 'test'
Requires-Dist: flake8 ; extra == 'test'
Requires-Dist: black ; extra == 'test'
Requires-Dist: isort ; extra == 'test'
Requires-Dist: pytest-cov ; extra == 'test'
Requires-Dist: mypy ; extra == 'test'
Requires-Dist: gitchangelog ; extra == 'test'
Requires-Dist: pdoc3 ; extra == 'test'
Requires-Dist: scikit-learn ; extra == 'test'
Requires-Dist: ipdb ; extra == 'test'
Requires-Dist: tqdm ; extra == 'test'
